IreneAPIWrapper/__init__.py
IreneAPIWrapper/exceptions.py
IreneAPIWrapper/models/__init__.py
IreneAPIWrapper/models/access.py
IreneAPIWrapper/models/affiliation.py
IreneAPIWrapper/models/automedia.py
IreneAPIWrapper/models/banphrase.py
IreneAPIWrapper/models/biasgame.py
IreneAPIWrapper/models/callback.py
IreneAPIWrapper/models/channel.py
IreneAPIWrapper/models/client.py
IreneAPIWrapper/models/company.py
IreneAPIWrapper/models/difficulty.py
IreneAPIWrapper/models/display.py
IreneAPIWrapper/models/eightball.py
IreneAPIWrapper/models/fandom.py
IreneAPIWrapper/models/group.py
IreneAPIWrapper/models/groupalias.py
IreneAPIWrapper/models/guessinggame.py
IreneAPIWrapper/models/guild.py
IreneAPIWrapper/models/interactions.py
IreneAPIWrapper/models/language.py
IreneAPIWrapper/models/location.py
IreneAPIWrapper/models/media.py
IreneAPIWrapper/models/mode.py
IreneAPIWrapper/models/name.py
IreneAPIWrapper/models/notification.py
IreneAPIWrapper/models/person.py
IreneAPIWrapper/models/personalias.py
IreneAPIWrapper/models/position.py
IreneAPIWrapper/models/preloadcache.py
IreneAPIWrapper/models/reactionrolemessages.py
IreneAPIWrapper/models/reminder.py
IreneAPIWrapper/models/social.py
IreneAPIWrapper/models/statsupdater.py
IreneAPIWrapper/models/subscription.py
IreneAPIWrapper/models/tag.py
IreneAPIWrapper/models/tiktokaccount.py
IreneAPIWrapper/models/twitchaccount.py
IreneAPIWrapper/models/unscramblegame.py
IreneAPIWrapper/models/urban.py
IreneAPIWrapper/models/user.py
IreneAPIWrapper/models/userstatus.py
IreneAPIWrapper/models/wolfram.py
IreneAPIWrapper/models/base/__init__.py
IreneAPIWrapper/models/base/abstractmodel.py
IreneAPIWrapper/models/base/alias.py
IreneAPIWrapper/models/base/file.py
IreneAPIWrapper/models/base/mediasource.py
IreneAPIWrapper/models/base/receiver.py
IreneAPIWrapper/sections/__init__.py
IreneAPIWrapper-3.0.dist-info/METADATA
IreneAPIWrapper-3.0.dist-info/WHEEL
IreneAPIWrapper-3.0.dist-info/top_level.txt
IreneAPIWrapper-3.0.dist-info/RECORD
