Metadata-Version: 2.1
Name: IreneAPIWrapper
Version: 3.0
Summary: A wrapper for Irene's API and connects with a websocket connection.
Home-page: https://github.com/MujyKun/IreneAPIWrapper
Author: MujyKun
Author-email: mujy@irenebot.com
License: MIT License
Classifier: Development Status :: 5 - Production/Stable
Classifier: License :: OSI Approved :: MIT License
Classifier: Programming Language :: Python
Requires-Python: >=3.7
Requires-Dist: asyncio ==3.4.3
Requires-Dist: aiohttp ==3.8.1
